{
  "phases": [
    {
      "dir": "0-mvp",
      "status": "completed",
      "completed_at": "2026-05-24T12:22:09+0900"
    },
    {
      "dir": "1-visual-quality",
      "status": "completed",
      "completed_at": "2026-05-24T15:50:38+0900"
    },
    {
      "dir": "2-visual-polish",
      "status": "completed",
      "failed_at": "2026-05-24T18:51:14+0900",
      "completed_at": "2026-05-24T18:59:21+0900"
    },
    {
      "dir": "3-quick-fixes",
      "status": "completed",
      "completed_at": "2026-05-24T21:28:55+0900"
    },
    {
      "dir": "4-fish-interactions",
      "status": "completed",
      "completed_at": "2026-05-25T00:17:36+0900"
    },
    {
      "dir": "5-fish-species",
      "status": "completed",
      "completed_at": "2026-05-27T01:29:51+0900"
    }
  ]
}